easygoogletranslate/__init__.py
easygoogletranslate/easygoogletranslate.py
easygoogletranslate-0.0.4.dist-info/METADATA
easygoogletranslate-0.0.4.dist-info/WHEEL
easygoogletranslate-0.0.4.dist-info/top_level.txt
easygoogletranslate-0.0.4.dist-info/RECORD
