Metadata-Version: 2.1
Name: easygoogletranslate
Version: 0.0.4
Summary: Easy Google Translate: Unofficial Google Translate API
Home-page: https://github.com/ahmeterenodaci/easygoogletranslate
Author: Ahmet Eren Odacı
Author-email: ahmetererenodaci@gmail.com
Classifier: Programming Language :: Python :: 3
Classifier: License :: OSI Approved :: MIT License
Classifier: Operating System :: OS Independent
Requires-Python: >=3.5.5
